<?xml version="1.0" encoding="utf-8"?>
<ArticulatorSettings xmlns:xsi="http://www.w3.org/2001/XMLSchema-instance" xmlns:xsd="http://www.w3.org/2001/XMLSchema">
  <AnteriorPosteriorDistance>125.927</AnteriorPosteriorDistance>
  <IntercondylarDistance>109.9</IntercondylarDistance>
  <HeightUpperArticulatorPart>84.692</HeightUpperArticulatorPart>
  <HeightFrontPlate>0</HeightFrontPlate>
  <HeightIncisalNeedle>0.0</HeightIncisalNeedle>
  <ArticulatorPosition>
    <x>29.4</x>
    <y>-80</y>
    <z>-24.692</z>
  </ArticulatorPosition>
  <ArticulationPlaneLegRight>
    <x>-90.0</x>
    <y>-32.0</y>
    <z>43.692</z>
  </ArticulationPlaneLegRight>
  <ArticulationPlaneLegLeft>
    <x>90.0</x>
    <y>-32.0</y>
    <z>43.692</z>
  </ArticulationPlaneLegLeft>
  <ArticulationPlaneIncisalNeedle>
    <x>0.0</x>
    <!--<y>125.0</y>-->
    <y>5.0</y>
    <z>43.692</z>
  </ArticulationPlaneIncisalNeedle>
  <ArticulationPlaneIncisalNeedleMarkerLengthY>40.0</ArticulationPlaneIncisalNeedleMarkerLengthY>
  <CollapseBennettAngle>true</CollapseBennettAngle>
  <CollapseHeightIncisalNeedleOffset>false</CollapseHeightIncisalNeedleOffset>
  <CollapseTiltCondylarGuide>false</CollapseTiltCondylarGuide>
  <CollapseRotationAxis>true</CollapseRotationAxis>
  <CollapseRotationFrontplateY>true</CollapseRotationFrontplateY>
  <CollapseRotationFrontplateZ>true</CollapseRotationFrontplateZ>
  <CollapseTiltFrontplate>true</CollapseTiltFrontplate>
  <CollapseImmediateSideshift>false</CollapseImmediateSideshift>
  <CollapseBennettInsert>true</CollapseBennettInsert>
  <CollapseCondylarInsert>true</CollapseCondylarInsert>
  <FrontplateAdjustable>false</FrontplateAdjustable>
  <IncisalNeedleRotation>false</IncisalNeedleRotation>
  <RotationPointShift>0</RotationPointShift>
  <!--<FrontplateAdjustablePivotPoint><x>0.0</x><y>0.0</y><z>0.0</z></FrontplateAdjustablePivotPoint>-->
  <BennettAngleLeftParam>
    <Type>BennettAngleLeft</Type>
    <Value>15</Value>
    <MinValue>0</MinValue>
    <MaxValue>25</MaxValue>
  </BennettAngleLeftParam>
  <BennettAngleRightParam>
    <Type>BennettAngleRight</Type>
    <Value>15</Value>
    <MinValue>0</MinValue>
    <MaxValue>25</MaxValue>
  </BennettAngleRightParam>
  <TiltCondylarGuideLeftParam>
    <Type>TiltCondylarGuideLeft</Type>
    <Value>35</Value>
    <MinValue>-13</MinValue>
    <MaxValue>60</MaxValue>
  </TiltCondylarGuideLeftParam>
  <TiltCondylarGuideRightParam>
    <Type>TiltCondylarGuideRight</Type>
    <Value>35</Value>
    <MinValue>-13</MinValue>
    <MaxValue>60</MaxValue>
  </TiltCondylarGuideRightParam>
  <RotationFrontplateYLeftParam>
    <Type>RotationFrontplateYLeft</Type>
    <Value>0</Value>
    <MinValue>0</MinValue>
    <MaxValue>45</MaxValue>
  </RotationFrontplateYLeftParam>
  <RotationFrontplateYRightParam>
    <Type>RotationFrontplateYRight</Type>
    <Value>0</Value>
    <MinValue>0</MinValue>
    <MaxValue>45</MaxValue>
  </RotationFrontplateYRightParam>
  <RotationFrontplateZParam>
    <Type>RotationFrontplateZ</Type>
    <Value>0</Value>
    <MinValue>-60</MinValue>
    <MaxValue>60</MaxValue>
  </RotationFrontplateZParam>
  <TiltFrontplateParam>
    <Type>TiltFrontplate</Type>
    <Value>0</Value>
    <MinValue>0</MinValue>
    <MaxValue>60</MaxValue>
  </TiltFrontplateParam>
  <HeightIncisalNeedleOffsetParam>
    <Type>HeightIncisalNeedleOffset</Type>
    <Value>0</Value>
    <MinValue>-5</MinValue>
    <MaxValue>10</MaxValue>
  </HeightIncisalNeedleOffsetParam>
  <RetrusionParam>
    <Type>Retrusion</Type>
    <Value>0</Value>
    <MinValue>0</MinValue>
    <MaxValue>2</MaxValue>
  </RetrusionParam>
  <ShowArticulatorMeshes>true</ShowArticulatorMeshes>
  <ArticulatorMainParts>
    <Incisalneedle>
      <Filename>incisal_needle.stl</Filename>
    </Incisalneedle>
    <Frontplate>
      <Filename>incisal_plate.off</Filename>
    </Frontplate>
    <!--<BennettInserts><ArticulatorMesh><Id>BennettInsertMetal</Id><Filename>bennettinsert_right_metal.stl</Filename><ColorDiffuse>#afafaf</ColorDiffuse><Side>Right</Side></ArticulatorMesh><ArticulatorMesh><Id>BennettInsertMetal</Id><Filename>bennettinsert_left_metal.stl</Filename><ColorDiffuse>#afafaf</ColorDiffuse><Side>Left</Side></ArticulatorMesh><ArticulatorMesh><Id>BennettInsertRed</Id><Filename>bennettinsert_right_red.stl</Filename><ColorDiffuse>#FF0000</ColorDiffuse><Side>Right</Side></ArticulatorMesh><ArticulatorMesh><Id>BennettInsertRed</Id><Filename>bennettinsert_left_red.stl</Filename><ColorDiffuse>#FF0000</ColorDiffuse><Side>Left</Side></ArticulatorMesh></BennettInserts>-->
    <!--<CondylarInserts><ArticulatorMesh><Id>CondylarInsertWhite</Id><Filename>condylarcurvature_white_right.stl</Filename><ColorDiffuse>#FFFFFF</ColorDiffuse><Side>Right</Side></ArticulatorMesh><ArticulatorMesh><Id>CondylarInsertWhite</Id><Filename>condylarcurvature_white_left.stl</Filename><ColorDiffuse>#FFFFFF</ColorDiffuse><Side>Left</Side></ArticulatorMesh><ArticulatorMesh><Id>CondylarInsertGreen</Id><Filename>condylarcurvature_green_right.stl</Filename><ColorDiffuse>#00FF00</ColorDiffuse><Side>Right</Side></ArticulatorMesh><ArticulatorMesh><Id>CondylarInsertGreen</Id><Filename>condylarcurvature_green_left.stl</Filename><ColorDiffuse>#00FF00</ColorDiffuse><Side>Left</Side></ArticulatorMesh><ArticulatorMesh><Id>CondylarInsertRed</Id><Filename>condylarcurvature_red_right.stl</Filename><ColorDiffuse>#FF0000</ColorDiffuse><Side>Right</Side></ArticulatorMesh><ArticulatorMesh><Id>CondylarInsertRed</Id><Filename>condylarcurvature_red_left.stl</Filename><ColorDiffuse>#FF0000</ColorDiffuse><Side>Left</Side></ArticulatorMesh></CondylarInserts>-->
  </ArticulatorMainParts>
  <ArticulatorDecorations>
    <DecorationMeshes>
      <ArticulatorDecorationMesh>
        <Type>LowerPartDecorations</Type>
        <Filename>lowerparts_1.obj</Filename>
        <ColorAmbient>#ffff00</ColorAmbient>
        <ColorDiffuse>#ebeb00</ColorDiffuse>
        <ColorSpecular>#FFFFFF</ColorSpecular>
        <ColorEmissive>#404040</ColorEmissive>
        <ColorShininess>8.0</ColorShininess>
        <RenderEffectFile>silver</RenderEffectFile>
      </ArticulatorDecorationMesh>
      <ArticulatorDecorationMesh>
        <Type>UpperPartDecorations</Type>
        <Filename>upperparts_2.obj</Filename>
        <ColorAmbient>#050505</ColorAmbient>
        <ColorDiffuse>#080808</ColorDiffuse>
        <ColorSpecular>#FFFFFF</ColorSpecular>
        <ColorEmissive>#404040</ColorEmissive>
        <ColorShininess>8.0</ColorShininess>
        <RenderEffectFile>silver</RenderEffectFile>
      </ArticulatorDecorationMesh>
      <ArticulatorDecorationMesh>
        <Type>UpperPartDecorations</Type>
        <Filename>upperparts_1.obj</Filename>
        <ColorAmbient>#050505</ColorAmbient>
        <ColorDiffuse>#080808</ColorDiffuse>
        <ColorSpecular>#FFFFFF</ColorSpecular>
        <ColorEmissive>#404040</ColorEmissive>
        <ColorShininess>8.0</ColorShininess>
        <RenderEffectFile>silver</RenderEffectFile>
      </ArticulatorDecorationMesh>
      <ArticulatorDecorationMesh>
        <Type>IncisalNeedleDecorations</Type>
        <Filename>incisalparts_1.stl</Filename>
        <ColorAmbient>#ededed</ColorAmbient>
        <ColorDiffuse>#bebebe</ColorDiffuse>
        <ColorSpecular>#FFFFFF</ColorSpecular>
        <ColorEmissive>#404040</ColorEmissive>
        <ColorShininess>8.0</ColorShininess>
        <RenderEffectFile>silver</RenderEffectFile>
      </ArticulatorDecorationMesh>
      <ArticulatorDecorationMesh>
        <Type>IncisalNeedleDecorations</Type>
        <Filename>incisalparts_2.stl</Filename>
        <ColorAmbient>#ededed</ColorAmbient>
        <ColorDiffuse>#bebebe</ColorDiffuse>
        <ColorSpecular>#FFFFFF</ColorSpecular>
        <ColorEmissive>#404040</ColorEmissive>
        <ColorShininess>8.0</ColorShininess>
        <RenderEffectFile>black_metal</RenderEffectFile>
      </ArticulatorDecorationMesh>
      <ArticulatorDecorationMesh>
        <Type>SideshiftLeftDecorations</Type>
        <Filename>sideshiftleft.stl</Filename>
        <ColorAmbient>#d4d4d9</ColorAmbient>
        <ColorDiffuse>#aaaaae</ColorDiffuse>
        <ColorSpecular>#FFFFFF</ColorSpecular>
        <ColorEmissive>#404040</ColorEmissive>
        <ColorShininess>8.0</ColorShininess>
        <RenderEffectFile>black_metal</RenderEffectFile>
      </ArticulatorDecorationMesh>
      <ArticulatorDecorationMesh>
        <Type>SideshiftRightDecorations</Type>
        <Filename>sideshiftright.stl</Filename>
        <ColorAmbient>#d4d4d9</ColorAmbient>
        <ColorDiffuse>#aaaaae</ColorDiffuse>
        <ColorSpecular>#FFFFFF</ColorSpecular>
        <ColorEmissive>#404040</ColorEmissive>
        <ColorShininess>8.0</ColorShininess>
        <RenderEffectFile>black_metal</RenderEffectFile>
      </ArticulatorDecorationMesh>
      <ArticulatorDecorationMesh>
        <Type>CondyleRightDecorations</Type>
        <Filename>condyle_right_parts_1.obj</Filename>
        <ColorAmbient>#666666</ColorAmbient>
        <ColorDiffuse>#5c5c5c</ColorDiffuse>
        <ColorSpecular>#FFFFFF</ColorSpecular>
        <ColorEmissive>#404040</ColorEmissive>
        <RenderEffectFile>silver</RenderEffectFile>
        <ColorShininess>8.0</ColorShininess>
      </ArticulatorDecorationMesh>
      <ArticulatorDecorationMesh>
        <Type>CondyleLeftDecorations</Type>
        <Filename>condyle_left_parts_1.obj</Filename>
        <ColorAmbient>#666666</ColorAmbient>
        <RenderEffectFile>silver</RenderEffectFile>
        <ColorDiffuse>#5c5c5c</ColorDiffuse>
        <ColorSpecular>#FFFFFF</ColorSpecular>
        <ColorEmissive>#404040</ColorEmissive>
        <ColorShininess>8.0</ColorShininess>
      </ArticulatorDecorationMesh>
    </DecorationMeshes>
  </ArticulatorDecorations>
</ArticulatorSettings>