<?xml version="1.0"?>
<ArrayOfDentalProcessorInfo xmlns:xsi="http://www.w3.org/2001/XMLSchema-instance" xmlns:xsd="http://www.w3.org/2001/XMLSchema">


	<DentalProcessorInfo>
		<ProcessorType>DentalProcessors.AdjustingSituForAbutmentsProcessor</ProcessorType>
	</DentalProcessorInfo>
	
  <DentalProcessorInfo>
    <ProcessorType>DentalProcessors.AbutmentEditProcessor</ProcessorType>
  </DentalProcessorInfo>
  
  <DentalProcessorInfo>
    <ProcessorType>DentalProcessors.AbutmentBottomProcessor</ProcessorType>
  </DentalProcessorInfo>


  <DentalProcessorInfo>
    <ProcessorType>DentalProcessors.PrimaryTelescopeProcessor</ProcessorType>
  </DentalProcessorInfo>

 <DentalProcessorInfo>
    <ProcessorType>DentalProcessors.PreparationMarginProcessor</ProcessorType>
  </DentalProcessorInfo>
  
    <DentalProcessorInfo>
    <ProcessorType>DentalProcessors.InsertionDirectionProcessor</ProcessorType>
  </DentalProcessorInfo>
  
  
  <DentalProcessorInfo>
    <ProcessorType>DentalProcessors.CrownBottomProcessor</ProcessorType>
  </DentalProcessorInfo>
  
   <DentalProcessorInfo>
    <ProcessorType>DentalProcessors.LoadToothmodelProcessor</ProcessorType>
  </DentalProcessorInfo>
  
  <DentalProcessorInfo>
    <ProcessorType>DentalProcessors.LoadCustomToothmodelProcessor</ProcessorType>
  </DentalProcessorInfo>

  <DentalProcessorInfo>
    <ProcessorType>DentalProcessors.CorrectPlacementProcessorNew</ProcessorType>
  </DentalProcessorInfo>
  
  <DentalProcessorInfo>
    <ProcessorType>DentalProcessors.AdaptToothmodelProcessor</ProcessorType>
  </DentalProcessorInfo>
  

  <DentalProcessorInfo>
    <ProcessorType>DentalProcessors.FreeformProcessor</ProcessorType>
  </DentalProcessorInfo>

  <DentalProcessorInfo>
    <ProcessorType>DentalProcessors.FreeformTelescopeProcessor</ProcessorType>
  </DentalProcessorInfo>


    <DentalProcessorInfo>
    <ProcessorType>DentalProcessors.FreeformMergedProcessor</ProcessorType>
  </DentalProcessorInfo>
  
  <DentalProcessorInfo>
    <ProcessorType>DentalProcessors.FreeformEmergenceProfileProcessor</ProcessorType>
  </DentalProcessorInfo>
  
  <DentalProcessorInfo>
    <ProcessorType>DentalProcessors.ShrinkProcessor</ProcessorType>
  </DentalProcessorInfo>
  
  <DentalProcessorInfo>
    <ProcessorType>DentalProcessors.ConnectorProcessor</ProcessorType>
  </DentalProcessorInfo>
  
  <DentalProcessorInfo>
    <ProcessorType>DentalProcessors.NestingQueueProcessor</ProcessorType>
  </DentalProcessorInfo>

    <DentalProcessorInfo>
    <ProcessorType>DentalProcessors.MinThicknessProcessor</ProcessorType>
    </DentalProcessorInfo>

  <DentalProcessorInfo>
    <ProcessorType>DentalProcessors.MergePartsProcessor</ProcessorType>
  </DentalProcessorInfo>

  <DentalProcessorInfo>
    <ProcessorType>DentalProcessors.DeleteReconstructionsProcessor</ProcessorType>
  </DentalProcessorInfo>

  
    
  <DentalProcessorInfo>
    <ProcessorType>DentalProcessors.SaveToothBowProcessor</ProcessorType>
  </DentalProcessorInfo>

  <DentalProcessorInfo>
    <ProcessorType>DentalProcessors.WaxUpProcessor</ProcessorType>
  </DentalProcessorInfo>
  
  
  <DentalProcessorInfo>
    <ProcessorType>DentalProcessors.TiltProjectProcessor</ProcessorType>
  </DentalProcessorInfo>
  
    <DentalProcessorInfo>
    <ProcessorType>DentalProcessors.ReconstructionSelectionProcessor</ProcessorType>
  </DentalProcessorInfo>
  
  <DentalProcessorInfo>
    <ProcessorType>DentalProcessors.DeleteConnectorProcessor</ProcessorType>
  </DentalProcessorInfo>
  
  <DentalProcessorInfo>
    <ProcessorType>DentalProcessors.OffsetCopingProcessor</ProcessorType>
  </DentalProcessorInfo>

  <DentalProcessorInfo>
    <ProcessorType>DentalProcessors.OverPressProcessor</ProcessorType>
  </DentalProcessorInfo>

  <DentalProcessorInfo>
    <ProcessorType>DentalProcessors.BarProcessor</ProcessorType>
  </DentalProcessorInfo>

  <DentalProcessorInfo>
    <ProcessorType>DentalProcessors.InlayBottomProcessor</ProcessorType>
  </DentalProcessorInfo>

  <DentalProcessorInfo>
    <ProcessorType>DentalProcessors.OffsetInlayProcessor</ProcessorType>
  </DentalProcessorInfo>

  <DentalProcessorInfo>
    <ProcessorType>DentalProcessors.EmergenceProfileProcessor</ProcessorType>
  </DentalProcessorInfo>

  <DentalProcessorInfo>
    <ProcessorType>DentalProcessors.AbutmentMarkerProcessor</ProcessorType>
  </DentalProcessorInfo>
  
    <DentalProcessorInfo>
    <ProcessorType>DentalProcessors.ConnectToMesialProcessor</ProcessorType>
  </DentalProcessorInfo>  
  
   <DentalProcessorInfo>
    <ProcessorType>DentalProcessors.ConnectToDistalProcessor</ProcessorType>
  </DentalProcessorInfo>

  <DentalProcessorInfo>
    <ProcessorType>DentalProcessors.FreeformGingivaProcessor</ProcessorType>
  </DentalProcessorInfo>

  <DentalProcessorInfo>
    <ProcessorType>DentalProcessors.AdjustingSituProcessor</ProcessorType>
  </DentalProcessorInfo>

  <DentalProcessorInfo>
    <ProcessorType>DentalProcessors.FaceModelProcessor</ProcessorType>
  </DentalProcessorInfo>

  <DentalProcessorInfo>
    <ProcessorType>DentalProcessors.FaceCorrectPlacementProcessor</ProcessorType>
  </DentalProcessorInfo>

  <DentalProcessorInfo>
    <ProcessorType>DentalProcessors.CorrectAntagonistProcessor</ProcessorType>
  </DentalProcessorInfo>
  
    <!--DentalProcessorInfo>
    <ProcessorType>DentalProcessors.CorrectJawRelationProcessor</ProcessorType>
  </DentalProcessorInfo-->
  
    <DentalProcessorInfo>
    <ProcessorType>DentalProcessors.CorrectSituProcessor</ProcessorType>
  </DentalProcessorInfo>

    <DentalProcessorInfo>
    <ProcessorType>DentalProcessors.CorrectWaxupProcessor</ProcessorType>
  </DentalProcessorInfo>

  
      <DentalProcessorInfo>
    <ProcessorType>DentalProcessors.AbutmentInsertionDirectionProcessor</ProcessorType>
  </DentalProcessorInfo>

 
 <DentalProcessorInfo>
    <ProcessorType>DentalProcessors.CorrectPreparationMarginProcessor</ProcessorType>
  </DentalProcessorInfo>

  
 <DentalProcessorInfo>
    <ProcessorType>DentalProcessors.LoadAttachmentProcessor</ProcessorType>
  </DentalProcessorInfo>


 <DentalProcessorInfo>
    <ProcessorType>DentalProcessors.ScrewHoleDesignProcessor</ProcessorType>
  </DentalProcessorInfo>


 <DentalProcessorInfo>
    <ProcessorType>DentalProcessors.MeasuringPointsProcessor</ProcessorType>
  </DentalProcessorInfo>

     <DentalProcessorInfo>
    <ProcessorType>DentalProcessors.AntagonistEditProcessor</ProcessorType>
  </DentalProcessorInfo>

   <DentalProcessorInfo>
    <ProcessorType>DentalProcessors.MeshEditProcessor</ProcessorType>
  </DentalProcessorInfo>



   <DentalProcessorInfo>
    <ProcessorType>DentalProcessors.WaxupSituScanEditProcessor</ProcessorType>
  </DentalProcessorInfo>

 <DentalProcessorInfo>
    <ProcessorType>DentalProcessors.SetScrewChannelProcessor</ProcessorType>
  </DentalProcessorInfo>

    <DentalProcessorInfo>
    <ProcessorType>DentalProcessors.AbutmentScrewChannelManualBottomProcessor</ProcessorType>
 </DentalProcessorInfo>

    <DentalProcessorInfo>
    <ProcessorType>DentalProcessors.FreeformScanDataProcessor</ProcessorType>
  </DentalProcessorInfo>

  <DentalProcessorInfo>
    <ProcessorType>DentalProcessors.FreeformBarProcessor</ProcessorType>
  </DentalProcessorInfo>

  <DentalProcessorInfo>
    <ProcessorType>DentalProcessors.LoadSingleToothmodelProcessorNew</ProcessorType>
  </DentalProcessorInfo>

  <DentalProcessorInfo>
    <ProcessorType>DentalProcessors.JawRegistrationProcessor</ProcessorType>
  </DentalProcessorInfo>

  <DentalProcessorInfo>
    <ProcessorType>DentalProcessors.AdditionalScanRegistrationProcessor</ProcessorType>
  </DentalProcessorInfo>

      <DentalProcessorInfo>
    <ProcessorType>DentalProcessors.TransferSurfaceGeometryProcessor</ProcessorType>
  </DentalProcessorInfo>

      <DentalProcessorInfo>
    <ProcessorType>DentalProcessors.TelescopeInsertionDirectionProcessor</ProcessorType>
  </DentalProcessorInfo>

    <DentalProcessorInfo>
    <ProcessorType>DentalProcessors.ImplantReferenceProcessor</ProcessorType>
  </DentalProcessorInfo>


    <DentalProcessorInfo>
    <ProcessorType>DentalProcessors.BiteSplintTopProcessor</ProcessorType>
  </DentalProcessorInfo>

  <DentalProcessorInfo>
    <ProcessorType>DentalProcessors.BiteSplintBottomProcessor</ProcessorType>
  </DentalProcessorInfo>

  <DentalProcessorInfo>
    <ProcessorType>DentalProcessors.FreeformBiteSplintProcessor</ProcessorType>
  </DentalProcessorInfo>

  

  <DentalProcessorInfo>
    <ProcessorType>DentalProcessors.HybridCrownInsertionDirectionProcessor</ProcessorType>
  </DentalProcessorInfo>

  <DentalProcessorInfo>
    <ProcessorType>DentalProcessors.ProvisionalCrownTopProcessor</ProcessorType>
  </DentalProcessorInfo>  

 <DentalProcessorInfo>
    <ProcessorType>DentalProcessors.ProvisionalCrownBottomProcessor</ProcessorType>
  </DentalProcessorInfo>  

  <DentalProcessorInfo>
    <ProcessorType>DentalProcessors.MultiDieRegistrationProcessor</ProcessorType>
  </DentalProcessorInfo>
  
 
  <DentalProcessorInfo>
    <ProcessorType>DentalProcessors.ModelAlignmentProcessor</ProcessorType>
  </DentalProcessorInfo>  

  <DentalProcessorInfo>
    <ProcessorType>DentalProcessors.ModelSegmentationProcessor</ProcessorType>
  </DentalProcessorInfo>  

  <DentalProcessorInfo>
    <ProcessorType>DentalProcessors.ModelDieWithBoreProcessor</ProcessorType>
  </DentalProcessorInfo>
  
  <DentalProcessorInfo>
    <ProcessorType>DentalProcessors.ModelToothSegmentationProcessor</ProcessorType>
  </DentalProcessorInfo>

  <DentalProcessorInfo>
    <ProcessorType>DentalProcessors.ArticulatorRegistrationProcessor</ProcessorType>
  </DentalProcessorInfo>


  <DentalProcessorInfo>
    <ProcessorType>DentalProcessors.ModelAttachmentProcessor</ProcessorType>
  </DentalProcessorInfo>

  
  <DentalProcessorInfo>
    <ProcessorType>DentalProcessors.ModelToggleDieTypesProcessor</ProcessorType>
  </DentalProcessorInfo>

  <DentalProcessorInfo>
    <ProcessorType>DentalProcessors.ModelImplantProcessor</ProcessorType>
  </DentalProcessorInfo>
  
  <DentalProcessorInfo>
    <ProcessorType>DentalProcessors.FreeformModelProcessor</ProcessorType>
  </DentalProcessorInfo>
  
  <DentalProcessorInfo>
    <ProcessorType>DentalProcessors.LingualBandProcessor</ProcessorType>
  </DentalProcessorInfo>
  
  <DentalProcessorInfo>
    <ProcessorType>DentalProcessors.CopyAndPasteToothProcessor</ProcessorType>
  </DentalProcessorInfo>
  
    <DentalProcessorInfo>
    <ProcessorType>DentalProcessors.MirrorHealthyToSituProcessor</ProcessorType>
  </DentalProcessorInfo>
  
    <DentalProcessorInfo>
    <ProcessorType>DentalProcessors.ShowAxisProcessor</ProcessorType>
  </DentalProcessorInfo>
  
  <DentalProcessorInfo>
    <ProcessorType>DentalProcessors.JawMovementRegistrationProcessor</ProcessorType>
  </DentalProcessorInfo>
  
      <DentalProcessorInfo>
    <ProcessorType>DentalProcessors.CorrectPlacementOfReducedTeethProcessor</ProcessorType>
  </DentalProcessorInfo>
  
  <DentalProcessorInfo>
    <ProcessorType>DentalProcessors.ShrinkBarSegmentToothProcessor</ProcessorType>
  </DentalProcessorInfo>


  <DentalProcessorInfo>
    <ProcessorType>DentalProcessors.MergePartsToWaxupProcessor</ProcessorType>
  </DentalProcessorInfo>



   <DentalProcessorInfo>
    <ProcessorType>DentalProcessors.BridgeSplitProcessor</ProcessorType>
  </DentalProcessorInfo>

  <DentalProcessorInfo>
    <ProcessorType>DentalProcessors.BiteSplintConvertToWaxupProcessor</ProcessorType>
  </DentalProcessorInfo>    

  <!-- START TOTALPROSTHESIS PROCESSORS -->
	
  <DentalProcessorInfo>
    <ProcessorType>DentalProcessors.ProstheticModelAnalysisProcessor</ProcessorType>
  </DentalProcessorInfo>

  <DentalProcessorInfo>
    <ProcessorType>DentalProcessors.ProstheticToothPlacementProcessor</ProcessorType>
  </DentalProcessorInfo>

  <DentalProcessorInfo>
    <ProcessorType>DentalProcessors.CorrectProstheticToothPlacementProcessor</ProcessorType>
  </DentalProcessorInfo>

  <DentalProcessorInfo>
    <ProcessorType>DentalProcessors.ProstheticBaseBottomProcessor</ProcessorType>
  </DentalProcessorInfo>

  <DentalProcessorInfo>
    <ProcessorType>DentalProcessors.ProstheticBaseProcessor</ProcessorType>
  </DentalProcessorInfo>

  <DentalProcessorInfo>
    <ProcessorType>DentalProcessors.FreeformProstheticBaseProcessor</ProcessorType>
  </DentalProcessorInfo>
  
  <DentalProcessorInfo>
    <ProcessorType>DentalProcessors.AdaptProstheticBaseProcessor</ProcessorType>
  </DentalProcessorInfo>

  <!--<DentalProcessorInfo>
    <ProcessorType>DentalProcessors.ProstheticReportingProcessor</ProcessorType>
  </DentalProcessorInfo>-->

  <DentalProcessorInfo>
    <ProcessorType>DentalProcessors.ProstheticToothModelEditor</ProcessorType>
  </DentalProcessorInfo>
  
  <!-- END TOTALPROSTHESIS PROCESSORS -->
  
  <!-- START ENDO PROCESSORS -->
  <DentalProcessorInfo>
    <ProcessorType>DentalProcessors.PostMarkerProcessor</ProcessorType>
  </DentalProcessorInfo>
  
  <DentalProcessorInfo>
    <ProcessorType>DentalProcessors.PostPreparationProcessor</ProcessorType>
  </DentalProcessorInfo>
  
   <DentalProcessorInfo>
    <ProcessorType>DentalProcessors.EndoCrownPreparationProcessor</ProcessorType>
  </DentalProcessorInfo>
  
  <DentalProcessorInfo>
    <ProcessorType>DentalProcessors.PostBottomProcessor</ProcessorType>
  </DentalProcessorInfo>
  
  <DentalProcessorInfo>
    <ProcessorType>DentalProcessors.EndoCoreProcessor</ProcessorType>
  </DentalProcessorInfo>
  
  <DentalProcessorInfo>
    <ProcessorType>DentalProcessors.EndoCoreInsertionDirectionProcessor</ProcessorType>
  </DentalProcessorInfo>
  
  <DentalProcessorInfo>
    <ProcessorType>DentalProcessors.EndoBottomInsertionDirectionProcessor</ProcessorType>
  </DentalProcessorInfo>
  
  <DentalProcessorInfo>
    <ProcessorType>DentalProcessors.FreeformPostAndCoreProcessor</ProcessorType>
  </DentalProcessorInfo>
  <!-- END ENDO PROCESSORS -->

  <DentalProcessorInfo>
    <ProcessorType>DentalProcessors.ProductionBlankProcessor</ProcessorType>
  </DentalProcessorInfo>
  
  <DentalProcessorInfo>
    <ProcessorType>DentalProcessors.LoadBridgeModelsProcessor</ProcessorType>   
    <ShowOnlyIfHighPriority>true</ShowOnlyIfHighPriority>
  </DentalProcessorInfo>

  <DentalProcessorInfo>
    <ProcessorType>DentalProcessors.ShrinkTelescopesProcessor</ProcessorType>
  </DentalProcessorInfo>

  <DentalProcessorInfo>
	<ProcessorType>DentalProcessors.ShrinkGingivaProcessor</ProcessorType>
  </DentalProcessorInfo>
  


  <DentalProcessorInfo>
    <ProcessorType>DentalProcessors.WaxupBottomMarginProcessor</ProcessorType>
  </DentalProcessorInfo>

  <DentalProcessorInfo>
    <ProcessorType>DentalProcessors.WaxupBottomProcessor</ProcessorType>
  </DentalProcessorInfo>

  <DentalProcessorInfo>
    <ProcessorType>DentalProcessors.VirtualWaxUpBottomProcessor</ProcessorType>
  </DentalProcessorInfo>
    
  <DentalProcessorInfo>
    <ProcessorType>DentalProcessors.VirtualWaxUpBaseProcessor</ProcessorType>
  </DentalProcessorInfo>
  
  <DentalProcessorInfo>
    <ProcessorType>DentalProcessors.FreeformVirtualWaxUpBaseProcessor</ProcessorType>
  </DentalProcessorInfo>
  
  
  <DentalProcessorInfo>
    <ProcessorType>DentalProcessors.LoadBiteSplintModelsProcessor</ProcessorType>   
  </DentalProcessorInfo>

   <DentalProcessorInfo>
    <ProcessorType>DentalProcessors.ConvertLibraryModelToPonticProcessor</ProcessorType>
   </DentalProcessorInfo>

  
</ArrayOfDentalProcessorInfo>
